ucr_datasets/__init__.py
ucr_datasets/dataloaders.py
ucr_datasets/utils.py
ucr_datasets/data/ACSF1_TEST.tsv
ucr_datasets/data/ACSF1_TRAIN.tsv
ucr_datasets/data/Adiac_TEST.tsv
ucr_datasets/data/Adiac_TRAIN.tsv
ucr_datasets/data/AllGestureWiimoteX_TEST.tsv
ucr_datasets/data/AllGestureWiimoteX_TRAIN.tsv
ucr_datasets/data/AllGestureWiimoteY_TEST.tsv
ucr_datasets/data/AllGestureWiimoteY_TRAIN.tsv
ucr_datasets/data/AllGestureWiimoteZ_TEST.tsv
ucr_datasets/data/AllGestureWiimoteZ_TRAIN.tsv
ucr_datasets/data/ArrowHead_TEST.tsv
ucr_datasets/data/ArrowHead_TRAIN.tsv
ucr_datasets/data/BME_TEST.tsv
ucr_datasets/data/BME_TRAIN.tsv
ucr_datasets/data/Beef_TEST.tsv
ucr_datasets/data/Beef_TRAIN.tsv
ucr_datasets/data/BeetleFly_TEST.tsv
ucr_datasets/data/BeetleFly_TRAIN.tsv
ucr_datasets/data/BirdChicken_TEST.tsv
ucr_datasets/data/BirdChicken_TRAIN.tsv
ucr_datasets/data/CBF_TEST.tsv
ucr_datasets/data/CBF_TRAIN.tsv
ucr_datasets/data/Car_TEST.tsv
ucr_datasets/data/Car_TRAIN.tsv
ucr_datasets/data/Chinatown_TEST.tsv
ucr_datasets/data/Chinatown_TRAIN.tsv
ucr_datasets/data/ChlorineConcentration_TEST.tsv
ucr_datasets/data/ChlorineConcentration_TRAIN.tsv
ucr_datasets/data/CinCECGTorso_TEST.tsv
ucr_datasets/data/CinCECGTorso_TRAIN.tsv
ucr_datasets/data/Coffee_TEST.tsv
ucr_datasets/data/Coffee_TRAIN.tsv
ucr_datasets/data/Computers_TEST.tsv
ucr_datasets/data/Computers_TRAIN.tsv
ucr_datasets/data/CricketX_TEST.tsv
ucr_datasets/data/CricketX_TRAIN.tsv
ucr_datasets/data/CricketY_TEST.tsv
ucr_datasets/data/CricketY_TRAIN.tsv
ucr_datasets/data/CricketZ_TEST.tsv
ucr_datasets/data/CricketZ_TRAIN.tsv
ucr_datasets/data/Crop_TEST.tsv
ucr_datasets/data/Crop_TRAIN.tsv
ucr_datasets/data/DiatomSizeReduction_TEST.tsv
ucr_datasets/data/DiatomSizeReduction_TRAIN.tsv
ucr_datasets/data/DistalPhalanxOutlineAgeGroup_TEST.tsv
ucr_datasets/data/DistalPhalanxOutlineAgeGroup_TRAIN.tsv
ucr_datasets/data/DistalPhalanxOutlineCorrect_TEST.tsv
ucr_datasets/data/DistalPhalanxOutlineCorrect_TRAIN.tsv
ucr_datasets-0.0.6.dist-info/METADATA
ucr_datasets-0.0.6.dist-info/WHEEL
ucr_datasets-0.0.6.dist-info/top_level.txt
ucr_datasets-0.0.6.dist-info/RECORD
